{
    "levels": [
      {
        "level" : 1,
        "maxEnemies": 3,
        "enemies": [
          { "type": "Bat", "x": 200, "y": 100 },
          { "type": "Beatle", "x": 400, "y": 120 },
          { "type": "Bat", "x": 600, "y": 150 }
        ]
      },
      {
        "level" : 2,
        "maxEnemies": 3,
        "enemies": [
          {
            "type": "Bat",
            "path": [100, 100, 200, 100, 300, 100, 400, 100]
          },
          {
            "type": "Beatle",
            "path": [600, 150, 550, 150, 500, 150, 450, 150]
          },
          {
            "type": "Bat",
            "path": [150, 200, 250, 200, 350, 200, 450, 200]
          }
        ]
      },
      {
        "level": 3,
        "maxEnemies": 4,
        "enemies": [
          {
            "type": "Beatle",
            "path": [300, 50, 320, 100, 340, 50, 360, 100]
          },
          {
            "type": "Bat",
            "path": [100, 50, 120, 100, 140, 50, 160, 100]
          },
          {
            "type": "Bat",
            "path": [600, 50, 580, 100, 560, 50, 540, 100]
          },
          {
            "type": "Beatle",
            "path": [700, 50, 720, 100, 740, 50, 760, 100]
          }
        ]
      },
      {
        "level": 4,
        "maxEnemies": 5,
        "enemies": [
          {
            "type": "Bat",
            "path": [100, 0, 150, 50, 200, 0, 250, 50]
          },
          {
            "type": "Beatle",
            "path": [300, 0, 350, 50, 400, 0, 450, 50]
          },
          {
            "type": "Bat",
            "path": [500, 0, 550, 50, 600, 0, 650, 50]
          },
          {
            "type": "Beatle",
            "path": [12, 92, 157, 23, 281, 89, 426, 28, 550, 90, 683, 31]
            
          },
          {
            "type": "Bat",
            "path": [200, 0, 250, 50, 300, 0, 350, 50]
          }
        ]
      }
    ]
  }
